{
  "SBGR": {
    "icao": "SBGR",
    "nome": "Aeroporto Guarulhos",
    "cidade": "Guarulhos",
    "uf": "SP",
    "uso": "Publico",
    "usoPublico": true,
    "operacao": "IFR",
    "tipoOperacao": "IFR",
    "passageirosAno": 43000000,
    "comprimentoPista": 3700,
    "codigoNumero": 4,
    "codigoLetra": "E",
    "envergaduraMaxima": 65,
    "tipoAeronave": "grandes",
    "tipoOperacaoAVSEC": [
      "domestica",
      "internacional",
      "passageiros",
      "carga"
    ],
    "pista": true,
    "taxiway": true,
    "patio": true,
    "pavimentado": true,
    "sistemaEletrico": true,
    "operacaoNoturna": true,
    "baixaVisibilidade": true,
    "internacional": true,
    "possuiSinalizacaoLuminosa": true,
    "possuiBalizas": true,
    "possuiObstaculos": true,
    "possuiAreaInterditada": false,
    "possuiAreaSemSuporte": false,
    "possuiAreaAntesCabeceira": false,
    "possuiAreaForaServico": false,
    "possuiPontoTesteAltimetro": true
  },
  "SBSP": {
    "icao": "SBSP",
    "nome": "Aeroporto Congonhas",
    "cidade": "Sao Paulo",
    "uf": "SP",
    "uso": "Publico",
    "usoPublico": true,
    "operacao": "IFR",
    "tipoOperacao": "IFR",
    "passageirosAno": 22000000,
    "comprimentoPista": 1940,
    "codigoNumero": 4,
    "codigoLetra": "E",
    "envergaduraMaxima": 65,
    "tipoAeronave": "grandes",
    "tipoOperacaoAVSEC": [
      "domestica",
      "internacional",
      "passageiros",
      "carga"
    ],
    "pista": true,
    "taxiway": true,
    "patio": true,
    "pavimentado": true,
    "sistemaEletrico": true,
    "operacaoNoturna": true,
    "baixaVisibilidade": true,
    "internacional": true,
    "possuiSinalizacaoLuminosa": true,
    "possuiBalizas": true,
    "possuiObstaculos": true,
    "possuiAreaInterditada": false,
    "possuiAreaSemSuporte": false,
    "possuiAreaAntesCabeceira": false,
    "possuiAreaForaServico": false,
    "possuiPontoTesteAltimetro": true
  },
  "SBKP": {
    "icao": "SBKP",
    "nome": "Aeroporto Viracopos",
    "cidade": "Campinas",
    "uf": "SP",
    "uso": "Publico",
    "usoPublico": true,
    "operacao": "IFR",
    "tipoOperacao": "IFR",
    "passageirosAno": 12000000,
    "comprimentoPista": 3240,
    "codigoNumero": 4,
    "codigoLetra": "E",
    "envergaduraMaxima": 65,
    "tipoAeronave": "grandes",
    "tipoOperacaoAVSEC": [
      "domestica",
      "internacional",
      "passageiros",
      "carga"
    ],
    "pista": true,
    "taxiway": true,
    "patio": true,
    "pavimentado": true,
    "sistemaEletrico": true,
    "operacaoNoturna": true,
    "baixaVisibilidade": true,
    "internacional": true,
    "possuiSinalizacaoLuminosa": true,
    "possuiBalizas": true,
    "possuiObstaculos": true,
    "possuiAreaInterditada": false,
    "possuiAreaSemSuporte": false,
    "possuiAreaAntesCabeceira": false,
    "possuiAreaForaServico": false,
    "possuiPontoTesteAltimetro": true
  },
  "SBBR": {
    "icao": "SBBR",
    "nome": "Aeroporto Brasilia",
    "cidade": "Brasilia",
    "uf": "DF",
    "uso": "Publico",
    "usoPublico": true,
    "operacao": "IFR",
    "tipoOperacao": "IFR",
    "passageirosAno": 15000000,
    "comprimentoPista": 3300,
    "codigoNumero": 4,
    "codigoLetra": "E",
    "envergaduraMaxima": 65,
    "tipoAeronave": "grandes",
    "tipoOperacaoAVSEC": [
      "domestica",
      "internacional",
      "passageiros",
      "carga"
    ],
    "pista": true,
    "taxiway": true,
    "patio": true,
    "pavimentado": true,
    "sistemaEletrico": true,
    "operacaoNoturna": true,
    "baixaVisibilidade": true,
    "internacional": true,
    "possuiSinalizacaoLuminosa": true,
    "possuiBalizas": true,
    "possuiObstaculos": true,
    "possuiAreaInterditada": false,
    "possuiAreaSemSuporte": false,
    "possuiAreaAntesCabeceira": false,
    "possuiAreaForaServico": false,
    "possuiPontoTesteAltimetro": true
  },
  "SBGO": {
    "icao": "SBGO",
    "nome": "Aeroporto Goiania",
    "cidade": "Goiania",
    "uf": "GO",
    "uso": "Publico",
    "usoPublico": true,
    "operacao": "IFR",
    "tipoOperacao": "IFR",
    "passageirosAno": 3500000,
    "comprimentoPista": 2500,
    "codigoNumero": 4,
    "codigoLetra": "E",
    "envergaduraMaxima": 65,
    "tipoAeronave": "grandes",
    "tipoOperacaoAVSEC": [
      "domestica",
      "internacional",
      "passageiros",
      "carga"
    ],
    "pista": true,
    "taxiway": true,
    "patio": true,
    "pavimentado": true,
    "sistemaEletrico": true,
    "operacaoNoturna": true,
    "baixaVisibilidade": true,
    "internacional": false,
    "possuiSinalizacaoLuminosa": true,
    "possuiBalizas": true,
    "possuiObstaculos": true,
    "possuiAreaInterditada": false,
    "possuiAreaSemSuporte": false,
    "possuiAreaAntesCabeceira": false,
    "possuiAreaForaServico": false,
    "possuiPontoTesteAltimetro": true
  }
}